horsephrase/__init__.py
horsephrase/__main__.py
horsephrase/_guess_guess.py
horsephrase/_implementation.py
horsephrase/_regen_words.py
horsephrase/py.typed
horsephrase/words.txt
horsephrase-2022.12.9.1.dist-info/LICENSE
horsephrase-2022.12.9.1.dist-info/METADATA
horsephrase-2022.12.9.1.dist-info/WHEEL
horsephrase-2022.12.9.1.dist-info/entry_points.txt
horsephrase-2022.12.9.1.dist-info/top_level.txt
horsephrase-2022.12.9.1.dist-info/RECORD
