Metadata-Version: 2.1
Name: horsephrase
Version: 2022.12.9.1
Summary: Secure password generator.
Home-page: https://github.com/glyph/horsephrase/
Author: Glyph
Author-email: glyph@twistedmatrix.com
Maintainer: Glyph
Maintainer-email: glyph@twistedmatrix.com
License: MIT
Classifier: Programming Language :: Python :: 3.9
Classifier: Programming Language :: Python :: 3.10
Classifier: Programming Language :: Python :: 3.11
Requires-Python: >=3
License-File: LICENSE
Requires-Dist: typing-extensions ; python_version < "3.8"
Provides-Extra: dev
Requires-Dist: requests ; extra == 'dev'
